<locale language="en">
  <s key="PJP_LBL_NEW_PROJECT">New Project…</s>
  <s key="PJP_LBL_QUICK_PROJECT">Quick Project</s>
  <s key="PJP_LBL_OPEN_PROJECT">Open Project…</s>
  <s key="PJP_LBL_PROJECT_REFRESH">Refresh</s>
  <s key="PJP_LBL_PROJECT_RENAME">Rename Project…</s>
  <s key="PJP_LBL_PROJECT_CLOSE">Close Project</s>
  <s key="PJP_LBL_PROJECT_DELETE">Delete Project…</s>
  <s key="PJP_MI_PROJECT_TEST">Test Project</s>
  <s key="PJT_LBL_PUBLISH_MOVIE">Publish Movie</s>
  <s key="PJP_LBL_PROJECT_PUBLISH">Publish Project</s>
  <s key="PJP_LBL_PROJECT_PROPS">Project Properties…</s>
  <s key="PJP_LBL_CLEAR_RECENTFILES">Clear Recent Files</s>
  <s key="PJP_LBL_PANEL_PREFS">Panel Preferences…</s>
  <s key="CFL_LBL_FILETYPE_TXT">Text File</s>
  <s key="CFL_LBL_FILETYPE_AS">ActionScript File</s>
  <s key="CFL_LBL_FILETYPE_JSFL">Flash JavaScript File</s>
  <s key="CFL_LBL_FILETYPE_XML">XML File</s>
  <s key="CFL_LBL_FILETYPE_AS3_FLA">Flash Document</s>
  <s key="DLG_TTL_CREATE_CLASS">Create Class</s>
  <s key="DLG_TTL_CREATE_FILE">Create File</s>
  <s key="DLG_TTL_CREATE_FOLDER">Create Folder</s>
  <s key="DLG_TTL_FILE_PROPS">File Properties</s>
  <s key="DLG_TTL_PANEL_PREFS">Panel Preferences</s>
  <s key="DLG_TTL_PROJECT_PROPS">Project Properties</s>
  <s key="DLG_TTL_CREATE_PROJECT">Create New Project</s>
  <s key="DLG_MSG_RENAME_PROJECT">New name:</s>
  <s key="CFL_LBL_SELECT_FILE_TYPE">-- Select A File Type --</s>
  <s key="PJT_LBL_NO_PROJECT">No Active Project</s>
  <s key="DLG_TTL_BROWSE_FOR_ROOT">Select the project folder:</s>
  <s key="CPJ_LBL_CLASS_LANGUAGE">Class template:</s>
  <s key="CPJ_LBL_FILE_NAME">File name:</s>
  <s key="GBL_LBL_OPEN_AFTER_CREATE">Open file after creation</s>
  <s key="CCD_LBL_BOUND">Bind class to library symbol</s>
  <s key="CCD_LBL_USE_SELECTED">Use selected library symbol</s>
  <s key="CCD_LBL_FILL_UI">Declare stage instances</s>
  <s key="CCD_LBL_FULL_LINKAGE_PATH">Use qualified class name for linkage</s>
  <s key="SET_LBL_CHANGE_DEFAULT_FILTERS">Change default filters</s>
  <s key="SET_LBL_TOGGLE_HIDDEN_FILES">Show hidden files</s>
  <s key="SET_LBL_HIDE_FILTERS">Hide files or folders beginning with:</s>
  <s key="LBL_HIDE_FILES_WITH">list of single-characters to omit</s>
  <s key="SET_LBL_TOGGLE_RECENT_FILES">Show recent files</s>
  <s key="LOC_LBL_SHOW_LOCATIONS">Specify additional source folders outside of the root project folder</s>
  <s key="PJT_LBL_LOCATIONS">Locations</s>
  <s key="CFL_LBL_FILE_TYPE">File type:</s>
  <s key="FPR_LBL_FILE_LOCATION">Location:</s>
  <s key="FPR_LBL_FILE_SIZE">Size:</s>
  <s key="FPR_LBL_FILE_CREATED">Created:</s>
  <s key="FPR_LBL_FILE_MODIFIED">Modified:</s>
  <s key="FPR_LBL_FILE_ATTRIBUTES">Attributes:</s>
  <s key="LBL_FILE_PATH">Folder</s>
  <s key="CPJ_LBL_PROJECT_NAME">Project name:</s>
  <s key="FPR_LBL_FILE_READONLY">Read only</s>
  <s key="FPR_LBL_FILE_HIDDEN">Hidden</s>
  <s key="LBL_PACKAGE">Package:</s>
  <s key="LBL_NAME">Name:</s>
  <s key="LBL_MODIFIERS">Modifiers:</s>
  <s key="LBL_SUPERCLASS">Superclass:</s>
  <s key="RB_PUBLIC">public</s>
  <s key="RB_INTERNAL">internal</s>
  <s key="CHB_DYNAMIC">dynamic</s>
  <s key="CHB_FINAL">final</s>
  <s key="TAB_LBL_CLASSES">Classes</s>
  <s key="TAB_LBL_SETTINGS">Settings</s>
  <s key="TAB_LBL_LOCATIONS">Locations</s>
  <s key="DLG_TTL_PROJECT_EXISTS">Project Exists</s>
  <s key="DLG_MSG_PROJECT_EXISTS">The specified project path already exists.</s>
  <s key="DLG_TTL_CREATE_FILE_ERROR">Error creating file.</s>
  <s key="DLG_MSG_CREATE_FILE_ERROR">The file could not be created.</s>
  <s key="DLG_FILE_EXISTS_ERROR_TITLE">File Exists</s>
  <s key="DLG_FILE_EXISTS_ERROR_BODY">Do you wish to overwrite the file?</s>
  <s key="DLG_CREATE_FOLDERR_ERROR_BODY">The folder could not be created.</s>
  <s key="DLG_TTL_CREATE_FOLDER_ERROR">Error creating folder.</s>
  <s key="LBL_INTERFACES">Interfaces</s>
  <s key="GBL_LBL_AS1">ActionScript 1.0</s>
  <s key="GBL_LBL_AS2">ActionScript 2.0</s>
  <s key="GBL_LBL_AS3">ActionScript 3.0</s>
  <s key="CB_LANG_INTERFACE">Interface</s>
  <s key="DLG_TTL_BROWSE_CLASSPATH">Find a new location to store your classes.</s>
  <s key="DLG_TTL_BROWSE_TEMPLATE">Browse for a new template file.</s>
  <s key="DLG_MSG_INVALID_TEMPLATE">Template files must be an ActionScript or text file.</s>
  <s key="GBL_LBL_LANGUAGE_OPTION">Change settings for:</s>
  <s key="JSFL_TO_MANY_ITEMS">To many items selected.</s>
  <s key="JSFL_NO_ITEMS_SELECTED">You must select a symbol in the FLA's library.</s>
  <s key="JSFL_ITEM_NOT_MOVIE_CLIP">Selected Item is not a movie clip.</s>
  <s key="JSFL_ITEM_EXISTS">Item already exists in that path.</s>
  <s key="JSFL_ITEM_CREATE_FAIL">Failed to create new library item.</s>
  <s key="JSFL_CREATE_FOLDER_FAIL">Could not create folder</s>
  <s key="JSFL_NO_CLASS_TEMPLATE">Class template '{fileName}' not found.  Please update the class template URI in Project Properties -&gt; Classes tab.</s>
  <s key="JSFL_BAD_URI">Bad URI Passed in</s>
  <s key="JSFL_LINKAGE_EXISTS">The current linkage already exists, and can not be overwritten.\nThe export settings for this item will not be changed.</s>
  <s key="JSFL_CLASS_EXISTS">The current class already exists, and can not be overwritten.The export settings for this item will not be changed.</s>
  <s key="PJT_LBL_OPEN_FILE">Open File</s>
  <s key="PJT_LBL_MAKE_DEFAULT">Make Default Document</s>
  <s key="PJT_LBL_DELETE_FILE">Delete File</s>
  <s key="PJT_LBL_TEST_MOVIE">Test Movie</s>
  <s key="PJT_LBL_EXPORT_SWF">Export SWF</s>
  <s key="PJT_LBL_PROPERTIES">Properties</s>
  <s key="DLG_ERROR_DELETING_FILE">Error Deleting File</s>
  <s key="JSFL_FILE_EXISTS_ERROR">File Exists</s>
  <s key="LBL_PROJECT_LANG">ActionScript version:</s>
  <s key="PJP_LBL_CLEAR_MENU">Clear Menu</s>
  <s key="PJP_LBL_HELP">Help…</s>
  <s key="DLG_TTL_ERROR">Error</s>
  <s key="DLG_MSG_SAVE_DOCUMENT">You need to save your document first.</s>
  <s key="DLG_FILE_DOSENT_EXIST">The specified file doesn't exist.</s>
  <s key="PJT_LBL_RECENT_FILES">Recent Files</s>
  <s key="CM_REMOVE_FROM_LIST">Remove From List</s>
  <s key="DLG_MSG_CONFIRM_PROJECT_DELETE">Are you sure you want to delete '{projectName}'?</s>
  <s key="DLG_MSG_NOT_ALL_FILES_REMOVED">All the files could not be deleted.</s>
  <s key="DPJ_LBL_DO_NOT_DELETE_CONTENTS">Do not delete contents</s>
  <s key="DPJ_LBL_DELETE_CONTENTS">Also delete contents under '{projectUri}'</s>
  <s key="DPJ_LBL_DELETE_CONTENTS_WARNING">Contents cannot be deleted if the project is currently open in Flash Builder.</s>
  <s key="DLG_TTL_CONFIRM_PROJECT_DELETE">Confirm Project Delete</s>
  <s key="PJP_LBL_PROJECTS">Projects</s>
  <s key="DLG_FOLDER_NOT_VALID_PROJECT_TITLE">Folder not valid project</s>
  <s key="DLG_FOLDER_NOT_VALID_PROJECT_BODY">The selected folder is not a valid project.</s>
  <s key="DLG_TTL_PROJECT_ROOT_NOT_FOUND">Invalid Project Root</s>
  <s key="PJT_LBL_OPEN_IN_FINDER">Open in Finder</s>
  <s key="DLG_TTL_NO_DEFAULT_APP">No Default File</s>
  <s key="DLG_MSG_NO_DEFAULT_APP">Test Project requires that a FLA file be marked as the Default Document.</s>
  <s key="PJT_LBL_OPEN_IN_EXPLORER">Open in Explorer</s>
  <s key="DLG_TTL_WARNING">Warning</s>
  <s key="PJT_LBL_PUBLISHLIST_TIP">Publish Items ({numCompileItems})</s>
  <s key="PJT_LBL_NO_FILES">No files</s>
  <s key="FPR_LBL_FOLDER_SIZE">({folderSize}) {numFiles} files</s>
  <s key="PJT_LBL_PINNED_FOLDER">Pinned:</s>
  <s key="PJT_LBL_NO_PROJECT_SELECTED">No project selected</s>
  <s key="PJP_LBL_PUBLISHLIST_ADD">Add file to Publish List</s>
  <s key="PJP_LBL_PUBLISHLIST_REMOVE">Remove file from Publish List</s>
  <s key="MI_TEST_WITH_CURRENT">Test with current</s>
  <s key="DLG_MSG_NO_DOCUMENT">No active fla file.</s>
  <s key="PJT_LBL_DELETE_FOLDER">Delete Folder</s>
  <s key="DLG_SUCCESS">Success</s>
  <s key="DLG_MSG_RENAME_LOCATION">New name for '{locationName}'</s>
  <s key="FPR_LBL_FILE_FOLDER">Folder</s>
  <s key="DLG_MSG_CREATE_FOLDER_ERROR">Folder could not be created.</s>
  <s key="DLG_TTL_OPEN_PROJECT">Select a folder containing a Flash project.</s>
  <s key="CFL_LBL_CREATE_FILE_PROMPT">&lt;Untitled File&gt;</s>
  <s key="LBL_RENAME_TITLE">Rename</s>
  <s key="DLG_LBL_BROWSE_FOR_ROOT">Browse For Root</s>
  <s key="DLG_LBL_DELETE_PROJECT_REFERENCE">Delete Project Reference</s>
  <s key="CPJ_LBL_ROOT_FOLDER">Root folder:</s>
  <s key="CCD_LBL_CLASS">Class:</s>
  <s key="CCD_LBL_CREATE_NEW">Create new library symbol</s>
  <s key="CHB_OPEN_CLASS_FILE">Open class file after creation</s>
  <s key="PJT_LBL_OPEN_PARENT_IN_EXPLORER">Open Enclosing Folder in Explorer</s>
  <s key="PJT_LBL_OPEN_PARENT_IN_FINDER">Open Enclosing Folder in Finder</s>
  <s key="CFO_LBL_FOLDER_NAME">Folder name:</s>
  <s key="GBL_LBL_CLASSPATH">Save classes in:</s>
  <s key="GBL_LBL_CLASS_TEMPLATE">Class template:</s>
  <s key="GBL_LBL_BOUND_CLASS_TEMPLATE">Class template for a symbol class:</s>
  <s key="DLG_TTL_BROWSE_LOCATION">Browse for a new location.</s>
  <s key="LBL_REMOVE_LOCATION">Remove location</s>
  <s key="CP_REMOVE_LOCATION">Remove location "{locationName}"?</s>
  <s key="DLG_PROJECT_EXISTS_AT_URI">The project "{projectName}" already exists in this location.  Do you wish to open this project?</s>
  <s key="PJT_LBL_PATH_NOT_FOUND">Folder path doesn't exist.</s>
  <s key="DLG_MSG_INVALID_PROJECT_PATH">Your project path must point to a valid folder.</s>
  <s key="DLG_MSG_INVALID_CLASS_PATH">You need to set a valid location to store your classes.</s>
  <s key="DLG_TTL_RENAME_LOCATION">Rename Location</s>
  <s key="SET_LBL_TOGGLE_CLASS_FOLDER">Show classes folder</s>
  <s key="PRF_LBL_RESET_DEFAULTS">Reset To Defaults</s>
  <s key="GBL_LBL_OK">OK</s>
  <s key="GBL_LBL_CANCEL">Cancel</s>
  <s key="GBL_LBL_BROWSE">Browse</s>
  <s key="GBL_LBL_REMOVE">Remove</s>
  <s key="GBL_LBL_ADD">Add</s>
  <s key="LOC_LBL_RENAME">Rename Location…</s>
  <s key="GBL_LBL_NO">No</s>
  <s key="GBL_LBL_YES">Yes</s>
  <s key="DLG_TTL_DELETE_ERROR">Error Deleting File or Folder</s>
  <s key="PJT_LBL_DELETE">Delete</s>
  <s key="PJT_LBL_UNPIN">Unpin '{folderName}'</s>
  <s key="PJT_LBL_PIN">Pin '{folderName}'</s>
  <s key="PJT_LBL_TEST_PROJECT">Test Project</s>
  <s key="PJT_LBL_NEW_FILE">New File</s>
  <s key="PJT_LBL_NEW_CLASS">Create Class</s>
  <s key="PJT_LBL_NEW_FOLDER">New Folder</s>
  <s key="DLG_TTL_DELETE_CONFIRM">Confirm Delete</s>
  <s key="DLG_MSG_DELETE_ERROR">Cannot delete '{fileName}'. Close any programs that might be using '{fileName}' and try again.</s>
  <s key="DLG_MSG_DELETE_CONFIRM">Are you sure you want to delete '{fileName}' from the file system?</s>
  <s key="DLG_TTL_INVALID_TEMPLATE">Invalid File Type</s>
  <s key="CCD_LBL_CREATE">Create Class</s>
  <s key="CFL_LBL_FILE_NAME">File name:</s>
  <s key="CFL_LBL_CREATE">Create File</s>
  <s key="CFO_LBL_CREATE">Create File</s>
  <s key="DLG_TTL_INVALID_PROJECT_PATH">Project Path Invalid</s>
  <s key="FPR_LBL_FILE_TYPE">File type:</s>
  <s key="DLG_TTL_INVALID_CLASS_PATH">Invalid classpath</s>
  <s key="DLG_TTL_NOT_ALL_FILES_REMOVED">Warning</s>
  <s key="GBL_LBL_UNTITLED_PROJECT">Untitled Project</s>
  <s key="PJT_LBL_PIN_FOLDER">Pin Folder</s>
  <s key="PJT_LBL_FILE_NAME">File name:</s>
  <s key="DLG_TTL_FILE_NOTFOUND">File Not Found</s>
  <s key="DLG_MSG_FILE_NOTFOUND">The file '{fileName}' was not found.</s>
  <s key="DLG_MSG_PROJECT_ROOT_NOT_FOUND">The root folder is missing, or has been changed. Would you like to select a new one?</s>
  <s key="DLG_TTL_NO_DOCUMENT">Warning</s>
  <s key="DLG_TTL_UNSAVED_DOCUMENT">Document Not Saved</s>
  <s key="CPJ_LBL_CREATE">Create Project</s>
  <s key="LOC_LBL_LOCATIONS">Locations:</s>
  <s key="LOC_LBL_ADD">Add a location</s>
  <s key="LOC_LBL_REMOVE">Remove selected location</s>
  <s key="DLG_TTL_FOLDER_EXISTS">Error Creating Folder</s>
  <s key="DLG_MSG_FOLDER_EXISTS">The name '{folderName}' is already taken. Please choose a different name.</s>
  <s key="DLG_TTL_RENAME_PROJECT">Rename Project</s>
  <s key="DLG_MSG_FILE_EXISTS">Do you wish to overwrite the file "{fileName}"?</s>
  <s key="DLG_TTL_FILE_EXISTS">File Exists</s>
  <s key="DLG_MSG_UNSAVED_DOCUMENT">You need to save your document first.</s>
  <s key="DLG_MSG_REMOVE_LOCATION">Are you sure you want to remove the location "{locationName}"?</s>
  <s key="DLG_TTL_REMOVE_LOCATION">Remove Location</s>
  <s key="DLG_TTL_INVALID_PROJECT_VALUES">The following errors have occurred:</s>
  <s key="DLG_TTL_INVALID_PROJECT_NAME">Project name is invalid.</s>
  <s key="DLG_CFD_ERROR_TITLE">Invalid File Name</s>
  <s key="DLG_CFD_ERROR_MSG">You need to input a valid file name.</s>
  <s key="DLG_CFLD_ERROR_TITLE">Invalid folder name.</s>
  <s key="DLG_CFLD_ERROR_MSG">You need to input a valid folder name.</s>
  <s key="CFLD_LBL_CREATE">Create Folder</s>
  <s key="DLG_PPD_RESET_TITLE">Warning</s>
  <s key="DLG_PPD_RESET_MSG">This operation will reset ALL your panel preferences, and cannot be undone.  Do you wish to continue?</s>
  <s key="DLG_PROGPD_RESET_TITLE">Warning</s>
  <s key="DLG_PROGPD_RESET_MSG">This operation will reset ALL your project properties, and cannot be undone.  Do you wish to continue?</s>
  <s key="JSFL_COMPILELIST_NO_FILES">There are no files in the publish, please add some and try again.</s>
  <s key="JSFL_COMPILELIST_COMPILE_ERROR">There was an error while publishing the project. Please see the Compiler Errors panel for more information.</s>
  <s key="DLG_TTL_COMPILELIST_ERROR">Error Publishing Project</s>
  <s key="DLG_TTL_COMPILELIST_NO_FILES">No Files in Compile List</s>
  <s key="JSFL_CREATECLASS_EXISTS">Please enter a unique class name.</s>
  <s key="DLG_TTL_CREATE_CLASS_ERROR">Create Class Error</s>
  <s key="DLG_MSG_QUICK_PROJECT_EXISTS">'{fileName}' is part of an existing project. The project will be renamed '{flaName}' and '{fileName}' will be set as the default application.</s>
  <s key="PJT_LBL_OPEN_WITH_DEFAULT">Open File With Associated Application</s>
  <s key="DLG_PROJ_LIBRARY_TITLE">Library</s>
  <s key="DLG_PROJ_PATHS_TITLE">Paths</s>
  <s key="DLG_PROJ_SOURCE_TITLE">Source</s>
  <s key="DLG_PROJ_EXTERNAL_LIBRARY_TITLE">External Library</s>
  <s key="DLG_PROJ_FLEX_SDK">Flex SDK:</s>
  <s key="DLG_PROJ_SOURCE_LABEL">Folders containing ActionScript files:</s>
  <s key="DLG_PROJ_LIBRARY_LABEL">SWC files or folders containing SWC files:</s>
  <s key="DLG_PROJ_EXTERNAL_LIBRARY_LABEL">SWC files used as runtime shared libraries:</s>
  <s key="DLG_PATHS_BROWSE_FLEX">Browse for the location of the Flex SDK:</s>
  <s key="DLG_PATHS_BROWSE_SOURCE_FOLDER">Select the folder that contains the .as files you wish to import.</s>
  <s key="DLG_PATHS_BROWSE_SWC">Browse for a new SWC file.</s>
  <s key="DLG_PATHS_BROWSE_SWC_ERROR">Selected file must be a SWC.</s>
  <s key="DLG_PATH_MOVEUP_TIP">Move selected item up</s>
  <s key="DLG_PATH_MOVEDOWN_TIP">Move selected item down</s>
  <s key="GBL_BROWSE_FOLDER_TIP">Browse for folder</s>
  <s key="DLG_PATHS_BROWSE_SWC_TIP">Browse for SWC</s>
  <s key="DLG_PATHS_BROWSE_SWC_FOLDER">Select the folder that contains the .swc files you wish to import.</s>
  <s key="DLG_PATHS_BROWSE_EXTERNAL_LIBRARY_FOLDER">Select the folder that contains the .swc files you wish to use as runtime shared libraries.</s>
  <s key="JSFL_TEST_MOVIE_ERROR_TITLE">Error Testing Flash File</s>
  <s key="JSFL_TEST_MOVIE_ERROR">There was an error while attempting to test your flash file.</s>
  <s key="JSFL_PUBLISH_MOVIE_ERROR_TITLE">Error Publishing Flash File</s>
  <s key="JSFL_PUBLISH_MOVIE_ERROR">There was an error while attempting to publish your flash file.</s>
  <s key="DLG_UPDATE_LOCATIONS_TITLE">Update Changed Locations</s>
  <s key="DLG_UPDATE_LOCATIONS_DESC">The following locations cannot be found. Please update them with valid paths.  **Any unchanged paths will be removed.</s>
  <s key="DLG_UPDATE_LOCATIONS_WARNING">{selectCount} locations will be removed.  Do you wish to continue?</s>
  <s key="DLG_PATHS_EXISTS_TITLE">Path Exists</s>
  <s key="DLG_PATHS_EXISTS_BODY">The path you are trying to set already exists.</s>
  <s key="DLG_INVALID_FLEX_SDK">Directory does not contain a Flex SDK.</s>
  <s key="TIP_AS3_ONLY">Paths are not supported for ActionScript 2.0 projects</s>
  <s key="DLG_PATHS_ADD_FOLDER">Add new path</s>
  <s key="DLG_PATHS_REMOVE_FOLDER">Remove selected path</s>
  <s key="SWC_FILE_TYPE_NAME">Flash Component</s>
  <s key="AS_FILE_TYPE_NAME">Actionscript File</s>
  <s key="DLG_CLASS_PATH_MISSING">Default class folder not found.  Please update where you save your classes in Project Properties -&gt; Classes tab.</s>
  <s key="DLG_MISSING_COMPILE_LIST_ITEMS">The following files could not be found: {fileList}</s>
  <s key="FILE_ERR_PARENT_DOESNT_EXIST">Enclosing folder path doesn't exist.  Cannot create file.</s>
  <s key="FOLDER_ERR_PARENT_DOESNT_EXIST">Enclosing folder path doesn't exist.  Cannot create folder</s>
  <s key="SELECT_PROJECT_MENU_TIP">Project</s>
  <s key="OPTIONS_MENU_TIP">Options</s>
  <s key="CFL_LBL_PLAYER">Player:</s>
  <s key="CFL_LBL_ACTIONSCRIPT">Script:</s>
  <s key="CPJ_LBL_DEFAULT_DOC_NAME">Default document name:</s>
  <s key="DLG_TTL_BROWSE_FOR_DEFAULT_DOC">Select the default document:</s>
  <s key="FLASH_DOC_NAME">Flash Document</s>
  <s key="DLG_TTL_PROJECT_DELETED_EXT">Project Deleted</s>
  <s key="DLG_MSG_PROJECT_DELETED_EXT">The project {projectName} has been deleted from disk and will be removed from the Project panel.</s>
  <s key="CREATE_PROJECT_AS_MISMATCH">The class template ActionScript version must match the default document's ActionScript version.</s>
  <s key="CPJ_LBL_CREATE_DEFAULT_DOC">Create default document</s>
  <s key="CREATE_PROJECT_MISSING_FILENAME">Default document name is invalid.</s>
  <s key="PJP_LBL_OPEN_PROJECT_IN_EXPLORER">Open In Explorer</s>
  <s key="PJP_LBL_OPEN_PROJECT_IN_FINDER">Open In Finder</s>
</locale>
